idiap_devtools/__init__.py
idiap_devtools/click.py
idiap_devtools/logging.py
idiap_devtools/python.py
idiap_devtools/utils.py
idiap_devtools/gitlab/__init__.py
idiap_devtools/gitlab/changelog.py
idiap_devtools/gitlab/release.py
idiap_devtools/gitlab/runners.py
idiap_devtools/scripts/__init__.py
idiap_devtools/scripts/badges.py
idiap_devtools/scripts/changelog.py
idiap_devtools/scripts/cli.py
idiap_devtools/scripts/getpath.py
idiap_devtools/scripts/jobs.py
idiap_devtools/scripts/lasttag.py
idiap_devtools/scripts/release.py
idiap_devtools/scripts/runners.py
idiap_devtools/scripts/settings.py
idiap_devtools-2.1.0.dist-info/METADATA
idiap_devtools-2.1.0.dist-info/WHEEL
idiap_devtools-2.1.0.dist-info/entry_points.txt
idiap_devtools-2.1.0.dist-info/RECORD
