Metadata-Version: 2.4
Name: idiap-devtools
Version: 2.1.0
Summary: A *pot-pourri* of various tools required to develop python packages at Idiap's GitLab infrastructure
Project-URL: documentation, https://idiap-devtools.readthedocs.io/en/v2.1.0/
Project-URL: homepage, https://pypi.org/project/idiap-devtools
Project-URL: repository, https://gitlab.idiap.ch/software/idiap-devtools
Project-URL: changelog, https://gitlab.idiap.ch/software/idiap-devtools/-/releases
Author-email: Andre Anjos <andre.anjos@idiap.ch>
License-Expression: BSD-3-Clause
Classifier: Development Status :: 4 - Beta
Classifier: Intended Audience :: Developers
Classifier: License :: OSI Approved :: BSD License
Classifier: Natural Language :: English
Classifier: Programming Language :: Python :: 3
Classifier: Topic :: Software Development :: Libraries :: Python Modules
Requires-Python: >=3.11
Requires-Dist: click>=8
Requires-Dist: gitpython
Requires-Dist: packaging
Requires-Dist: python-dateutil
Requires-Dist: python-gitlab
Requires-Dist: pytz
Requires-Dist: tomli
Requires-Dist: tomlkit
Provides-Extra: doc
Requires-Dist: auto-intersphinx; extra == 'doc'
Requires-Dist: furo; extra == 'doc'
Requires-Dist: sphinx; extra == 'doc'
Requires-Dist: sphinx-autodoc-typehints; extra == 'doc'
Requires-Dist: sphinx-click; extra == 'doc'
Requires-Dist: sphinx-copybutton; extra == 'doc'
Requires-Dist: sphinx-inline-tabs; extra == 'doc'
Provides-Extra: qa
Requires-Dist: pre-commit; extra == 'qa'
Provides-Extra: test
Requires-Dist: pytest; extra == 'test'
Requires-Dist: pytest-cov; extra == 'test'
